gammarers/aws_secure_flow_log_bucket/__init__.py
gammarers/aws_secure_flow_log_bucket/py.typed
gammarers/aws_secure_flow_log_bucket/_jsii/__init__.py
gammarers/aws_secure_flow_log_bucket/_jsii/aws-secure-flow-log-bucket@1.5.64.jsii.tgz
gammarers_aws_secure_flow_log_bucket-1.5.64.dist-info/LICENSE
gammarers_aws_secure_flow_log_bucket-1.5.64.dist-info/METADATA
gammarers_aws_secure_flow_log_bucket-1.5.64.dist-info/WHEEL
gammarers_aws_secure_flow_log_bucket-1.5.64.dist-info/top_level.txt
gammarers_aws_secure_flow_log_bucket-1.5.64.dist-info/RECORD
