Metadata-Version: 2.1
Name: gammarers.aws-secure-flow-log-bucket
Version: 1.5.64
Summary: Specific AWS VPC FlowLog Bucket
Home-page: https://github.com/gammarers/aws-secure-flow-log-bucket.git
Author: yicr<yicr@users.noreply.github.com>
License: Apache-2.0
Project-URL: Source, https://github.com/gammarers/aws-secure-flow-log-bucket.git
Classifier: Intended Audience :: Developers
Classifier: Operating System :: OS Independent
Classifier: Programming Language :: JavaScript
Classifier: Programming Language :: Python :: 3 :: Only
Classifier: Programming Language :: Python :: 3.9
Classifier: Programming Language :: Python :: 3.10
Classifier: Programming Language :: Python :: 3.11
Classifier: Typing :: Typed
Classifier: Development Status :: 5 - Production/Stable
Classifier: License :: OSI Approved
Requires-Python: ~=3.9
License-File: LICENSE
Requires-Dist: aws-cdk-lib <3.0.0,>=2.80.0
Requires-Dist: constructs <11.0.0,>=10.0.5
Requires-Dist: gammarers.aws-secure-bucket <1.5.0,>=1.4.1
Requires-Dist: gammarers.aws-secure-log-bucket <1.8.0,>=1.7.0
Requires-Dist: jsii <2.0.0,>=1.113.0
Requires-Dist: publication >=0.0.3
Requires-Dist: typeguard <4.3.0,>=2.13.3
